{
    "package-id" : "ans.fhir.fr.pdsm",
    "version" : "3.0.1",
    "path" : "https://interop.esante.gouv.fr/ig/fhir/pdsm/3.0.1",
    "mode" : "milestone",
    "status" : "release",
    "sequence" : "Releases",
    "title" : "Partage de Documents de Santé en mobilité (PDSm)",
    "desc" : "Ajout flux de publication simplifié IHE (usage MES), précisions contenu DocumentReference.content.attachment.url, mise à jour dépendance IHE MHD 4.1.0 --> 4.2.0",
    "ci-build" : "https://build.interop.esante.gouv.fr/ig/fhir/pdsm",
    "category" : "Clinical Documents",
    "introduction" : "Il s’agit d’un volet de la couche service spécifiant les modalités de partage de documents sans contraindre ces derniers. Les spécifications liées aux documents de santé constituent les volets de la couche métier du CI-SIS."
  }